pytest_docker_compose/__init__.py
pytest_docker_compose/plugin.py
pytest_docker_compose_v2-0.2.0.dist-info/METADATA
pytest_docker_compose_v2-0.2.0.dist-info/WHEEL
pytest_docker_compose_v2-0.2.0.dist-info/entry_points.txt
pytest_docker_compose_v2-0.2.0.dist-info/licenses/LICENSE
pytest_docker_compose_v2-0.2.0.dist-info/RECORD
