Metadata-Version: 2.4
Name: pytest-docker-compose-v2
Version: 0.2.0
Summary: Manages Docker containers during your integration tests
Project-URL: repository, https://github.com/radusuciu/pytest-docker-compose-v2
Author: Radu Suciu, Thomas Meckel, Roald Storm, Phoenix Zerin
License: Apache
License-File: LICENSE
Keywords: docker compose,pytest
Classifier: Development Status :: 4 - Beta
Classifier: Framework :: Pytest
Classifier: Intended Audience :: Developers
Classifier: License :: OSI Approved :: Apache Software License
Classifier: Operating System :: OS Independent
Classifier: Programming Language :: Python
Classifier: Programming Language :: Python :: 3 :: Only
Classifier: Programming Language :: Python :: 3.10
Classifier: Programming Language :: Python :: 3.11
Classifier: Programming Language :: Python :: 3.12
Classifier: Programming Language :: Python :: 3.13
Classifier: Programming Language :: Python :: 3.14
Classifier: Topic :: Software Development :: Testing
Requires-Python: >=3.10
Requires-Dist: pytest<10,>=7.2.2
Requires-Dist: python-on-whales<1,>=0.69.0
